{"key":"content:zh:2.guide:3.directory-structure:13.server.md","generatedAt":"2022-07-12T12:13:02.453Z","mtime":"2022-07-12T12:13:02.452Z","slug":"server","title":"server","position":"000200030013","to":"/guide/directory-structure/server","draft":false,"page":true,"language":"zh","icon":"IconDirectory","head":{"title":"Server directory"},"empty":false,"description":"","body":{"raw":"---\nicon: IconDirectory\ntitle: server\nhead.title: Server directory\n---\n\n# Server directory\n\n::ReadMore{link=\"/guide/features/server-routes\"}\n","ast":{"type":"root","children":[{"type":"element","tag":"prose-h1","props":{"class":"d-heading-title","id":"server-directory"},"children":[{"type":"text","value":"Server directory"}]},{"type":"text","value":"\n"},{"type":"element","tag":"read-more","props":{"link":"/guide/features/server-routes"},"children":[]}]},"toc":{"title":"","searchDepth":2,"depth":2,"links":[]}}}